{
	"obligations": [
		{
			"identification": {
				"incomeSourceType": "ITSA",
				"referenceNumber": "AB123456A",
				"referenceType": "NINO"
			},
			"obligationDetails": [
				{
					"status": "O",
					"inboundCorrespondenceFromDate": "2020-02-28",
					"inboundCorrespondenceToDate": "2021-02-28",
					"inboundCorrespondenceDateReceived": "2022-01-24",
					"inboundCorrespondenceDueDate": "2023-02-28",
					"periodKey": "#001"
				},
				{
					"status": "O",
					"inboundCorrespondenceFromDate": "2020-02-28",
					"inboundCorrespondenceToDate": "2021-02-28",
					"inboundCorrespondenceDateReceived": "2022-01-24",
					"inboundCorrespondenceDueDate": "2023-02-28",
					"periodKey": "#002"
				},
				{
					"status": "O",
					"inboundCorrespondenceFromDate": "2020-02-28",
					"inboundCorrespondenceToDate": "2021-02-28",
					"inboundCorrespondenceDueDate": "2023-02-28",
					"periodKey": "#003"
				},
				{
					"status": "O",
					"inboundCorrespondenceFromDate": "2021-02-28",
					"inboundCorrespondenceToDate": "2022-01-28",
					"inboundCorrespondenceDueDate": "2023-01-28",
					"periodKey": "#004"
				}
			]
		}
	]
}
